ncompare/Comparison.py
ncompare/__init__.py
ncompare/console.py
ncompare/core.py
ncompare/getters.py
ncompare/path_and_string_operations.py
ncompare/printing.py
ncompare/sequence_operations.py
ncompare/utility_types.py
ncompare-1.14.1.dist-info/METADATA
ncompare-1.14.1.dist-info/WHEEL
ncompare-1.14.1.dist-info/entry_points.txt
ncompare-1.14.1.dist-info/licenses/LICENSE
ncompare-1.14.1.dist-info/RECORD
