Metadata-Version: 2.4
Name: ncompare
Version: 1.14.1
Summary: Compare the structure of two NetCDF files at the command line
Author-email: Daniel Kaufman <daniel.kaufman@nasa.gov>
License-Expression: Apache-2.0
License-File: LICENSE
Classifier: Environment :: Console
Classifier: Intended Audience :: Science/Research
Classifier: Operating System :: MacOS
Classifier: Operating System :: Microsoft :: Windows
Classifier: Operating System :: POSIX :: Linux
Classifier: Programming Language :: Python :: 3.11
Classifier: Programming Language :: Python :: 3.12
Classifier: Programming Language :: Python :: 3.13
Classifier: Programming Language :: Python :: 3.14
Classifier: Topic :: Software Development :: Libraries :: Python Modules
Requires-Python: <4,>=3.11
Requires-Dist: colorama>=0.4.6
Requires-Dist: h5netcdf>=1.7.3
Requires-Dist: h5py>=3.15.1
Requires-Dist: netcdf4>=1.6.4
Requires-Dist: numpy>=2.4.0
Requires-Dist: openpyxl>=3.1.2
Requires-Dist: xarray>=2025.12.0
